srsinst/sr860/__init__.py
srsinst/sr860/__main__.py
srsinst/sr860/sr860 with sr542.taskconfig
srsinst/sr860/sr860.taskconfig
srsinst/sr860/instruments/__init__.py
srsinst/sr860/instruments/components.py
srsinst/sr860/instruments/get_instruments.py
srsinst/sr860/instruments/keys.py
srsinst/sr860/instruments/sr860.py
srsinst/sr860/instruments/visainterface.py
srsinst/sr860/instruments/vxi11interface.py
srsinst/sr860/plots/__init__.py
srsinst/sr860/plots/timeplot.py
srsinst/sr860/plots/twobytwosharexplot.py
srsinst/sr860/tasks/__init__.py
srsinst/sr860/tasks/assignparametertochannel.py
srsinst/sr860/tasks/autofunctiontask.py
srsinst/sr860/tasks/auxoutputtask.py
srsinst/sr860/tasks/configurereferencetask.py
srsinst/sr860/tasks/configuresineoutputtask.py
srsinst/sr860/tasks/datatransferfromdatachannelstask.py
srsinst/sr860/tasks/scanauxout1task.py
srsinst/sr860/tasks/scanauxout2task.py
srsinst/sr860/tasks/scanfrequencytask.py
srsinst/sr860/tasks/scanrefamplitudetask.py
srsinst/sr860/tasks/scanrefoffsettask.py
srsinst/sr860/tasks/selecttimebasetask.py
srsinst/sr860/tasks/setreferencetochoptask.py
srsinst/sr860/tasks/setreferencetodualtask.py
srsinst/sr860/tasks/setreferencetoexternaltask.py
srsinst/sr860/tasks/setreferencetoexternalwithsr542task.py
srsinst/sr860/tasks/setreferencetointernaltask.py
srsinst/sr860/tasks/sidntesttask.py
srsinst/sr860/tasks/signaltocurrentmodetask.py
srsinst/sr860/tasks/signaltovoltagemodetask.py
srsinst/sr860/tasks/simulatedplot.py
srsinst/sr860/tasks/streamingtask.py
srsinst_sr860-0.3.2.dist-info/LICENSE.txt
srsinst_sr860-0.3.2.dist-info/METADATA
srsinst_sr860-0.3.2.dist-info/WHEEL
srsinst_sr860-0.3.2.dist-info/entry_points.txt
srsinst_sr860-0.3.2.dist-info/top_level.txt
srsinst_sr860-0.3.2.dist-info/RECORD
