Metadata-Version: 2.1
Name: srsinst.sr860
Version: 0.3.2
Summary: Instrument driver package for the Lock-In Amplifiers, SR860 series from Stanford Research Systems
Author: Chulhoon Kim
License: MIT license
Project-URL: homepage, https://github.com/thinkSRS/srsinst.sr860
Project-URL: repository, https://github.com/thinkSRS/srsinst.sr860.git
Keywords: SR860,SR865A,SRS,Stanford Research Systems,lock-in amplifier
Classifier: Development Status :: 3 - Alpha
Classifier: Intended Audience :: Science/Research
Classifier: License :: OSI Approved :: MIT License
Classifier: Programming Language :: Python :: 3.7
Classifier: Programming Language :: Python :: 3.8
Classifier: Programming Language :: Python :: 3.9
Classifier: Programming Language :: Python :: 3.10
Classifier: Topic :: Scientific/Engineering
Requires-Python: >=3.7
License-File: LICENSE.txt
Requires-Dist: numpy
Requires-Dist: python-vxi11
Requires-Dist: srsgui>=0.4.5
Provides-Extra: full
Requires-Dist: matplotlib>=3.6.2; extra == "full"
Requires-Dist: pyside6; extra == "full"
